HeadersFormatter/HeadersFormatter.py
HeadersFormatter/__init__.py
HeadersFormatter-0.0.2.dist-info/LICENSE
HeadersFormatter-0.0.2.dist-info/METADATA
HeadersFormatter-0.0.2.dist-info/WHEEL
HeadersFormatter-0.0.2.dist-info/entry_points.txt
HeadersFormatter-0.0.2.dist-info/top_level.txt
HeadersFormatter-0.0.2.dist-info/RECORD
